django_hearthstone/__init__.py
django_hearthstone/cards/__init__.py
django_hearthstone/cards/admin.py
django_hearthstone/cards/models.py
django_hearthstone/cards/management/__init__.py
django_hearthstone/cards/management/commands/__init__.py
django_hearthstone/cards/management/commands/load_cards.py
django_hearthstone/cards/migrations/0001_initial.py
django_hearthstone/cards/migrations/0002_auto_20180321_1313.py
django_hearthstone/cards/migrations/0003_auto_20190701_1420.py
django_hearthstone/cards/migrations/0004_add_multi_class_group.py
django_hearthstone/cards/migrations/0005_explicit_primary_keys.py
django_hearthstone/cards/migrations/0006_card_multiple_classes.py
django_hearthstone/cards/migrations/0007_card_fabled_card_is_fabled_bundle_card.py
django_hearthstone/cards/migrations/__init__.py
django_hearthstone/scenarios/__init__.py
django_hearthstone/scenarios/admin.py
django_hearthstone/scenarios/models.py
django_hearthstone/scenarios/management/__init__.py
django_hearthstone/scenarios/management/commands/__init__.py
django_hearthstone/scenarios/management/commands/load_dbf.py
django_hearthstone/scenarios/migrations/0001_initial.py
django_hearthstone/scenarios/migrations/0002_explicit_primary_keys.py
django_hearthstone/scenarios/migrations/__init__.py
django_hearthstone-1.6.0.dist-info/METADATA
django_hearthstone-1.6.0.dist-info/WHEEL
django_hearthstone-1.6.0.dist-info/top_level.txt
django_hearthstone-1.6.0.dist-info/RECORD
