Metadata-Version: 2.4
Name: django-hearthstone
Version: 1.6.0
Summary: Hearthstone file models for Django
Home-page: https://github.com/HearthSim/django-hearthstone/
Download-URL: https://github.com/HearthSim/django-hearthstone/tarball/master
Author: Jerome Leclanche
Author-email: jerome@leclan.ch
Classifier: Development Status :: 5 - Production/Stable
Classifier: Environment :: Web Environment
Classifier: Framework :: Django
Classifier: Framework :: Django :: 3.2
Classifier: Framework :: Django :: 4.0
Classifier: Framework :: Django :: 4.1
Classifier: Framework :: Django :: 4.2
Classifier: Intended Audience :: Developers
Classifier: License :: OSI Approved :: MIT License
Classifier: Operating System :: OS Independent
Classifier: Programming Language :: Python
Classifier: Programming Language :: Python :: 3
Classifier: Programming Language :: Python :: 3.10
Classifier: Topic :: Games/Entertainment
Classifier: Topic :: Software Development :: Libraries :: Python Modules
Requires-Dist: Django>=3.2
Requires-Dist: django-intenumfield>=1.3
Requires-Dist: hearthstone
Dynamic: description-content-type
Dynamic: download-url
